<?xml version="1.0" encoding="Shift_JIS" ?><DOCHEAD><DOCINFO-G><FMT>ODR</FMT><DOCKIND>2</DOCKIND><DOCCODE></DOCCODE><DOC-TITLE></DOC-TITLE><DOCDATE></DOCDATE><ENDDATE></ENDDATE></DOCINFO-G><DOCFLG-G><ACT-FLG>1</ACT-FLG><IMG>0</IMG><ZEN-FLG>2</ZEN-FLG></DOCFLG-G><DOCNO-G><DOCNO></DOCNO><DOCSEQ></DOCSEQ><PDOCNO></PDOCNO><ODRNO></ODRNO></DOCNO-G><MEDINFO-G><HSPOT>1</HSPOT><DOCDP> 90</DOCDP><DOCWD></DOCWD></MEDINFO-G><RSV-G><RSVCNT>0</RSVCNT><GRPCODE></GRPCODE><GRPSFX></GRPSFX></RSV-G><PID-G><PID></PID><PID-NAME></PID-NAME><PID-SEX></PID-SEX><PID-BIRTH></PID-BIRTH><PID-AGE></PID-AGE></PID-G><DOCSTS-G><DEL-G><DEL-FLG>1</DEL-FLG><DEL-UID></DEL-UID><DEL-DATE></DEL-DATE><DEL-TERM>lsvwhdbs</DEL-TERM></DEL-G><UPD-G><UPD-FLG>1</UPD-FLG><UPD-UID></UPD-UID><UPD-DATE></UPD-DATE><UPD-TERM>lsvwhdbs</UPD-TERM></UPD-G><IRI-G><IRI-FLG>1</IRI-FLG><IRI-UID></IRI-UID><IRI-DATE></IRI-DATE><IRI-TERM>lsvwhdbs</IRI-TERM></IRI-G><BMCR-G><BMCR-FLG>1</BMCR-FLG><BMCR-UID></BMCR-UID><BMCR-DATE></BMCR-DATE><BMCR-TERM>lsvwhdbs</BMCR-TERM></BMCR-G></DOCSTS-G><CR-G><CR-UID>097187</CR-UID><CR-UNAME>河北　俊子</CR-UNAME><CR-JOB>035</CR-JOB><CR-DEP> 90</CR-DEP><CR-DATE></CR-DATE><CR-TERM>lsvwhdbs</CR-TERM></CR-G><OP-G><OP-UID>097187</OP-UID><OP-UNAME>河北　俊子</OP-UNAME><OP-JOB>035</OP-JOB><OP-DEP> 90</OP-DEP><OP-RID>097187</OP-RID><OP-RNAME>河北　俊子</OP-RNAME><OP-DATE></OP-DATE><OP-TERM>lsvwhdbs</OP-TERM></OP-G></DOCHEAD>